bordercollie/__init__.py
bordercollie/asrsummary.py
bordercollie/auth.py
bordercollie/sql.py
bordercollie/utils.py
bordercollie/apps/__init__.py
bordercollie/apps/collector.py
bordercollie/apps/merge_log_consumer.py
bordercollie/apps/monitor.py
bordercollie/apps/trans_record_consumer.py
bordercollie/apps/workflow.py
bordercollie/base/__init__.py
bordercollie/demos/__init__.py
bordercollie/demos/crontabs.py
bordercollie-0.0.15.dist-info/METADATA
bordercollie-0.0.15.dist-info/WHEEL
bordercollie-0.0.15.dist-info/entry_points.txt
bordercollie-0.0.15.dist-info/top_level.txt
bordercollie-0.0.15.dist-info/RECORD
