Metadata-Version: 2.1
Name: bordercollie
Version: 0.0.15
Summary: ok
Home-page: https://github.com/private_repo/
Author: slipper
Author-email: r2fscg@gmail.com
Classifier: Programming Language :: Python :: 3
Classifier: License :: OSI Approved :: MIT License
Classifier: Operating System :: OS Independent
Requires-Dist: simauth
Requires-Dist: aiomysql
Requires-Dist: fire
Requires-Dist: aioredis
Requires-Dist: codefast (>=0.9.9)
